makepass/__init__.py
makepass/__main__.py
makepass/makepass.py
makepass/data/words.txt
makepass-0.11.0.dist-info/DESCRIPTION.rst
makepass-0.11.0.dist-info/METADATA
makepass-0.11.0.dist-info/RECORD
makepass-0.11.0.dist-info/WHEEL
makepass-0.11.0.dist-info/entry_points.txt
makepass-0.11.0.dist-info/metadata.json
makepass-0.11.0.dist-info/top_level.txt
