Metadata-Version: 2.0
Name: makepass
Version: 0.11.0
Summary: A simple password generator based on https://xkcd.com/936/
Home-page: https://github.com/Lucretiel/MakePass
Author: Nathan West
Author-email: UNKNOWN
License: GPLv2
Platform: any
Classifier: Development Status :: 4 - Beta
Classifier: Environment :: Console
Classifier: License :: OSI Approved :: GNU General Public License v2 (GPLv2)
Classifier: Programming Language :: Python
Classifier: Programming Language :: Python :: 3
Classifier: Programming Language :: Python :: 3.3
Classifier: Programming Language :: Python :: 3.4
Classifier: Programming Language :: Python :: 3.5
Classifier: Programming Language :: Python :: 3.6
Classifier: Programming Language :: Python :: 3 :: Only
Classifier: Topic :: Utilities
Requires-Dist: autocommand (<3.0.0,>=2.1.0)
